MANIFEST.in
README.md
setup.cfg
setup.py
csrc/Array.cc
csrc/Array.h
csrc/ClassInfo.cc
csrc/ClassInfo.h
csrc/Env.h
csrc/EqGrNode.cc
csrc/EqGrNode.h
csrc/Eqclass.cc
csrc/Eqclass.h
csrc/FreqIt.cc
csrc/FreqIt.h
csrc/InvertDatabase.cc
csrc/InvertDatabase.h
csrc/Itemset.cc
csrc/Itemset.h
csrc/Lists.cc
csrc/Lists.h
csrc/Partition.cc
csrc/Partition.h
csrc/Sequence.cc
csrc/Sequence.h
csrc/SpadeArguments.cc
csrc/SpadeArguments.h
csrc/TransArray.cc
csrc/TransArray.h
csrc/argh.h
csrc/argv_parser.cc
csrc/argv_parser.h
csrc/calcdb.cc
csrc/calcdb.h
csrc/common.cc
csrc/common.h
csrc/dirent-win.h
csrc/exttpose.cc
csrc/exttpose.h
csrc/exttpose_main.cc
csrc/getconf.cc
csrc/getconf.h
csrc/getconf_main.cc
csrc/main.cc
csrc/makebin.cc
csrc/makebin.h
csrc/makebin_main.cc
csrc/spade_main.cc
csrc/test.cc
csrc/wrappers.cc
csrc/wrappers.h
pycspade/__init__.py
pycspade/cspade.cpp
pycspade/cspade.pyx
pycspade/helpers.py
pycspade/shortcuts.py
pycspade.egg-info/PKG-INFO
pycspade.egg-info/SOURCES.txt
pycspade.egg-info/dependency_links.txt
pycspade.egg-info/requires.txt
pycspade.egg-info/top_level.txt