Metadata-Version: 2.1
Name: pycspade
Version: 0.6.2
Summary: C-SPADE Python Implementation
Home-page: https://github.com/fzyukio/python-cspade
Author: ['Mohammed J. Zaki', 'Yukio Fukuzawa']
License: MIT
Keywords: cspade,c-spade,sequence mining
Platform: UNKNOWN
